mbus_gem_decoder/__init__.py
mbus_gem_decoder/conversion/__init__.py
mbus_gem_decoder/conversion/mbusmbus.py
mbus_gem_decoder/conversion/mbusmeter.py
mbus_gem_decoder/conversion/mbusmeterentry.py
mbus_gem_decoder/conversion/utils/__init__.py
mbus_gem_decoder/conversion/utils/helpers.py
mbus_gem_decoder/conversion/utils/mbustypes.py
mbus_gem_decoder/mbusdecode.py
mbus_gem_decoder-0.1.0.dist-info/WHEEL
mbus_gem_decoder-0.1.0.dist-info/METADATA
mbus_gem_decoder-0.1.0.dist-info/RECORD
