Metadata-Version: 2.1
Name: mbus-gem-decoder
Version: 0.1.0
Summary: MBUS-GEM decoder
License: GPLv3
Author: René
Author-email: rene.pihlak@ttu.ee
Requires-Python: >=3.8,<4.0
Classifier: License :: Other/Proprietary License
Classifier: Programming Language :: Python :: 3
Classifier: Programming Language :: Python :: 3.8
Classifier: Programming Language :: Python :: 3.9
Classifier: Programming Language :: Python :: 3.10
Classifier: Programming Language :: Python :: 3.11
